{"episode_list":[{"episode_id":"1","episode_name":"\u6d5c\u5ddd\u611b\u7d50\u5948Vi\uff9a\uff6f\uff7d\uff9d\uff74\uff8b\uff9f\uff7f\uff70\uff84\uff9e1","episode_voice":"0"},{"episode_id":"2","episode_name":"\u6d5c\u5ddd\u611b\u7d50\u5948Vo\uff9a\uff6f\uff7d\uff9d\uff74\uff8b\uff9f\uff7f\uff70\uff84\uff9e1","episode_voice":"0"},{"episode_id":"3","episode_name":"\u6d5c\u5ddd\u611b\u7d50\u5948Da\uff9a\uff6f\uff7d\uff9d\uff74\uff8b\uff9f\uff7f\uff70\uff84\uff9e1","episode_voice":"0"},{"episode_id":"4","episode_name":"\u6d5c\u5ddd\u611b\u7d50\u5948\uff7d\uff83\uff6f\uff8c\uff9f\uff71\uff6f\uff8c\uff9f\uff74\uff8b\uff9f\uff7f\uff70\uff84\uff9e1","episode_voice":"0"},{"episode_id":"5","episode_name":"\u6d5c\u5ddd\u611b\u7d50\u5948Vi\uff9a\uff6f\uff7d\uff9d\uff74\uff8b\uff9f\uff7f\uff70\uff84\uff9e2","episode_voice":"0"},{"episode_id":"6","episode_name":"\u6d5c\u5ddd\u611b\u7d50\u5948Vo\uff9a\uff6f\uff7d\uff9d\uff74\uff8b\uff9f\uff7f\uff70\uff84\uff9e2","episode_voice":"0"},{"episode_id":"7","episode_name":"\u6d5c\u5ddd\u611b\u7d50\u5948Da\uff9a\uff6f\uff7d\uff9d\uff74\uff8b\uff9f\uff7f\uff70\uff84\uff9e2","episode_voice":"0"},{"episode_id":"8","episode_name":"\u6d5c\u5ddd\u611b\u7d50\u5948\uff7d\uff83\uff6f\uff8c\uff9f\uff71\uff6f\uff8c\uff9f\uff74\uff8b\uff9f\uff7f\uff70\uff84\uff9e2","episode_voice":"0"}],"idol_message":"\uff71\uff85\uff80\u306e\uff7e\uff9d\uff7d\u306b\u4efb\u305b\u3066\u3042\u3052\u308b\uff61\uff8c\uff8c\uff6f\uff64\u8cac\u4efb\u91cd\u5927\u3088\uff61\u3057\u3063\u304b\u308a\u3068\uff7a\uff70\uff83\uff9e\uff68\uff88\uff70\uff84\u3057\u3066\u306d\uff61\u671f\u5f85\u3057\u3066\u308b\u308f\u2606","idol_attribute":"3"}